{
  "mission_system": {
    "refresh_time_utc": "00:00",
    "daily_limit": 3,
    "weekly_limit": 5,
    "auto_replace": true,
    "replace_cooldown_hours": 6
  },

  "daily_missions": [
    {
      "id": "catch_common_fish",
      "title": "Поймай 10 обычных рыб",
      "description": "Отличная разминка перед настоящей рыбалкой!",
      "goal": { "type": "catch", "rarity": "common", "count": 10 },
      "rewards": { "xp": 50, "kzc": 30 }
    },
    {
      "id": "catch_predators",
      "title": "Поймай 3 хищных рыб",
      "description": "Проверь свою реакцию на зубастых!",
      "goal": { "type": "catch_species", "species": ["pike", "zander", "asp"], "count": 3 },
      "rewards": { "xp": 75, "kzc": 50 }
    },
    {
      "id": "sell_fish",
      "title": "Продай 10 кг рыбы",
      "description": "Помоги местному рынку свежим уловом.",
      "goal": { "type": "sell_weight", "weight_kg": 10 },
      "rewards": { "xp": 60, "kzc": 80 }
    },
    {
      "id": "discover_new_location",
      "title": "Посети новую локацию",
      "description": "Исследуй неизвестные водоёмы.",
      "goal": { "type": "visit_location", "count": 1 },
      "rewards": { "xp": 100, "kzc": 100, "bonus_item": "bait_pack" }
    },
    {
      "id": "catch_trophy",
      "title": "Поймай трофейную рыбу",
      "description": "Испытай удачу и поймай редкий экземпляр.",
      "goal": { "type": "catch_trophy", "count": 1 },
      "rewards": { "xp": 150, "kzc": 200, "ngt": 1 }
    }
  ],

  "weekly_missions": [
    {
      "id": "week_total_catch",
      "title": "Поймай 100 рыб за неделю",
      "description": "Терпение и настойчивость — ключ к успеху.",
      "goal": { "type": "catch", "count": 100 },
      "rewards": { "xp": 500, "kzc": 300 }
    },
    {
      "id": "week_trophy_collector",
      "title": "Поймай 10 трофейных рыб",
      "description": "Набери коллекцию из самых редких уловов.",
      "goal": { "type": "catch_trophy", "count": 10 },
      "rewards": { "xp": 800, "kzc": 600, "ngt": 3 }
    },
    {
      "id": "week_seller",
      "title": "Продай 100 кг рыбы",
      "description": "Покажи, кто главный поставщик в регионе!",
      "goal": { "type": "sell_weight", "weight_kg": 100 },
      "rewards": { "xp": 1000, "kzc": 800 }
    },
    {
      "id": "week_explorer",
      "title": "Посети 3 разных водоёма",
      "description": "Каждый водоём хранит свои тайны.",
      "goal": { "type": "visit_location", "count": 3 },
      "rewards": { "xp": 600, "kzc": 400, "item": "hook_set" }
    },
    {
      "id": "week_event_participation",
      "title": "Прими участие в турнире",
      "description": "Докажи, что ты лучший рыболов!",
      "goal": { "type": "participate_event", "count": 1 },
      "rewards": { "xp": 1200, "kzc": 1000, "ngt": 5 }
    }
  ],

  "notes": "Файл определяет ежедневные и недельные задания. Обновляется автоматически Nikiton Cloud по таймеру UTC. Поддерживает автозамену и бонусы донатных игроков."
}
