{
  "statistics": {
    "general": {
      "total_play_time_minutes": 0,
      "total_sessions": 0,
      "first_login": null,
      "last_login": null,
      "days_active_total": 0
    },
    "fishing": {
      "total_fish_caught": 0,
      "total_weight_kg": 0,
      "largest_fish_weight_kg": 0,
      "rare_fish_caught": 0,
      "legendary_fish_caught": 0,
      "event_fish_caught": 0,
      "tournaments_won": 0,
      "tournaments_participated": 0
    },
    "economy": {
      "gold_earned": 0,
      "gold_spent": 0,
      "ncoin_spent": 0,
      "market_sales": 0,
      "market_purchases": 0,
      "donations_total_kzt": 0
    },
    "social": {
      "friends_added": 0,
      "friend_requests_sent": 0,
      "friend_requests_received": 0,
      "chats_sent": 0,
      "events_participated": 0,
      "competitions_joined": 0
    },
    "achievements": {
      "completed": [],
      "in_progress": [],
      "total_points": 0
    },
    "last_synced": null
  },
  "mechanics": {
    "track_in_real_time": true,
    "auto_update_on_event_end": true,
    "sync_with_leaderboards": true,
    "track_per_location": true,
    "track_per_equipment_type": true
  },
  "display_settings": {
    "show_total_weight": true,
    "show_largest_fish": true,
    "show_rare_catches": true,
    "show_tournament_stats": true,
    "show_market_stats": true,
    "show_activity_chart": true
  },
  "security": {
    "prevent_fake_data_submission": true,
    "validate_server_source": true,
    "log_stat_changes": true,
    "encrypt_player_stats": true
  },
  "sync_settings": {
    "auto_sync": true,
    "sync_interval_minutes": 20,
    "upload_on_logout": true,
    "restore_on_login": true
  },
  "last_update": "2025-10-30T00:00:00Z"
}
